credex001/__init__.py
credex001/extractor.py
credex001-1.0.0.dist-info/LICENSE
credex001-1.0.0.dist-info/METADATA
credex001-1.0.0.dist-info/WHEEL
credex001-1.0.0.dist-info/top_level.txt
credex001-1.0.0.dist-info/RECORD
