Metadata-Version: 2.2
Name: credex001
Version: 1.0.0
Summary: A tool to extract email and password pairs from HTML files
Author: a random dude
Author-email: jcccadet3175@example.com
Classifier: Programming Language :: Python :: 3
Classifier: License :: OSI Approved :: MIT License
Classifier: Operating System :: OS Independent
License-File: LICENSE
Requires-Dist: bs4
Dynamic: author
Dynamic: author-email
Dynamic: classifier
Dynamic: description
Dynamic: description-content-type
Dynamic: requires-dist
Dynamic: summary
